xpcs_correlator-0.2.0.dist-info/licenses/LICENSE
xpcscorr/__init__.py
xpcscorr/__init__.pyi
xpcscorr/core/__init__.py
xpcscorr/core/base.py
xpcscorr/core/utils.py
xpcscorr/correlators/__init__.py
xpcscorr/correlators/base.py
xpcscorr/correlators/dense/__init__.py
xpcscorr/correlators/dense/chunked.py
xpcscorr/correlators/dense/reference.py
xpcscorr/correlators/sparse/__init__.py
xpcscorr/correlators/sparse/base.py
xpcscorr/correlators/sparse/chunked_numba.py
xpcs_correlator-0.2.0.dist-info/METADATA
xpcs_correlator-0.2.0.dist-info/WHEEL
xpcs_correlator-0.2.0.dist-info/top_level.txt
xpcs_correlator-0.2.0.dist-info/RECORD
