Metadata-Version: 2.4
Name: xpcs-correlator
Version: 0.2.0
Summary: XPCS correlation calculations for synchrotron experiments
Author-email: Maciej Jankowski <maciej.jankowski@esrf.fr>
License-Expression: MIT
Project-URL: Repository, https://gitlab.esrf.fr/mj/xpcs_developments/xpcscorr
Classifier: Development Status :: 3 - Alpha
Classifier: Programming Language :: Python :: 3
Classifier: Programming Language :: Python :: 3.10
Classifier: Programming Language :: Python :: 3.11
Classifier: Programming Language :: Python :: 3.12
Classifier: Intended Audience :: Science/Research
Classifier: Topic :: Scientific/Engineering
Requires-Python: >=3.10
License-File: LICENSE
Requires-Dist: numpy
Requires-Dist: numba
Requires-Dist: dask
Requires-Dist: dask_jobqueue
Requires-Dist: h5py
Requires-Dist: hdf5plugin
Requires-Dist: threadpoolctl
Provides-Extra: dev
Requires-Dist: pytest; extra == "dev"
Requires-Dist: memory_profiler; extra == "dev"
Requires-Dist: line_profiler; extra == "dev"
Requires-Dist: ruff; extra == "dev"
Requires-Dist: twine; extra == "dev"
Requires-Dist: scipy; extra == "dev"
Provides-Extra: doc
Requires-Dist: sphinx; extra == "doc"
Requires-Dist: sphinx-rtd-theme; extra == "doc"
Requires-Dist: sphinxcontrib-napoleon; extra == "doc"
Requires-Dist: nbsphinx; extra == "doc"
Requires-Dist: nbclient; extra == "doc"
Requires-Dist: nbformat; extra == "doc"
Requires-Dist: nbconvert; extra == "doc"
Requires-Dist: jupyter; extra == "doc"
Requires-Dist: pandoc; extra == "doc"
Requires-Dist: numpy; extra == "doc"
Dynamic: license-file
